[
  {
    "timestamp_utc": "2025-08-28T11:45:20.009Z",
    "context_application_version": "1.2.71.421",
    "context_conn_country": "AU",
    "context_device_manufacturer": "Micro-Star International Co., Ltd.",
    "context_device_model": "Cyborg 14 A13VE",
    "context_device_type": "desktop",
    "context_os_name": "windows",
    "context_os_version": "10.0.26100",
    "context_receiver_service_timestamp": 1756381546239,
    "context_time": 1756381520009,
    "message_audio_driver": "",
    "message_buffer_size": 0,
    "message_buffered_ms": 4,
    "message_driver_prebuffer_ms": null,
    "message_estimated_frame_loss": 0,
    "message_file_byte_offset": 131072,
    "message_file_byte_total": -1,
    "message_file_id": "mMSmxNmTFb34V3ElA6oPpvz0nRA=",
    "message_max_buffer_size": 65536,
    "message_playback_id": "auPUY/1oR8Ze8EUlFjQEHA==",
    "message_position_ms": 1364,
    "message_target_buffer": 1048576,
    "message_total_prebuffer_ms": null,
    "message_track": "spotify:track:3yRZ7wWTVYFgn5vcUjL2Pz"
  },
  {
    "timestamp_utc": "2025-09-17T03:42:59.298Z",
    "context_application_version": "9.0.78.1116",
    "context_conn_country": "AU",
    "context_device_manufacturer": "OPPO",
    "context_device_model": "CPH2625",
    "context_device_type": "mobile",
    "context_os_name": "android",
    "context_os_version": "15",
    "context_receiver_service_timestamp": 1758080586652,
    "context_time": 1758080579298,
    "message_audio_driver": "AndroidAudioDriver",
    "message_buffer_size": 0,
    "message_buffered_ms": 0,
    "message_driver_prebuffer_ms": null,
    "message_estimated_frame_loss": 0,
    "message_file_byte_offset": 112642,
    "message_file_byte_total": -1,
    "message_file_id": "R9YyMGexTsVNnvFFf2hwiT3KgZM=",
    "message_max_buffer_size": 79892,
    "message_playback_id": "UlEsmAMz0uR35rBoYRpfOA==",
    "message_position_ms": 9225,
    "message_target_buffer": 1048576,
    "message_total_prebuffer_ms": null,
    "message_track": "spotify:track:6sAFHFV7OWuSYuTNslP2HI"
  },
  {
    "timestamp_utc": "2025-09-12T04:58:01.623Z",
    "context_application_version": "1.2.71.421",
    "context_conn_country": "AU",
    "context_device_manufacturer": "Micro-Star International Co., Ltd.",
    "context_device_model": "Cyborg 14 A13VE",
    "context_device_type": "desktop",
    "context_os_name": "windows",
    "context_os_version": "10.0.26100",
    "context_receiver_service_timestamp": 1757653095915,
    "context_time": 1757653081623,
    "message_audio_driver": "",
    "message_buffer_size": 118448,
    "message_buffered_ms": 1023,
    "message_driver_prebuffer_ms": null,
    "message_estimated_frame_loss": 0,
    "message_file_byte_offset": 6966960,
    "message_file_byte_total": 6966960,
    "message_file_id": "k1puurjLyyhiM7Jg4qS8bGoWgHM=",
    "message_max_buffer_size": 1048576,
    "message_playback_id": "3BFNU8QDtLbgIQPRUN1TQw==",
    "message_position_ms": 191794,
    "message_target_buffer": 1048576,
    "message_total_prebuffer_ms": null,
    "message_track": "spotify:track:63bAGRSSX2V1hhPSP2NpBC"
  },
  {
    "timestamp_utc": "2025-08-28T11:45:29.614Z",
    "context_application_version": "1.2.71.421",
    "context_conn_country": "AU",
    "context_device_manufacturer": "Micro-Star International Co., Ltd.",
    "context_device_model": "Cyborg 14 A13VE",
    "context_device_type": "desktop",
    "context_os_name": "windows",
    "context_os_version": "10.0.26100",
    "context_receiver_service_timestamp": 1756381546239,
    "context_time": 1756381529614,
    "message_audio_driver": "",
    "message_buffer_size": 0,
    "message_buffered_ms": 4,
    "message_driver_prebuffer_ms": null,
    "message_estimated_frame_loss": 0,
    "message_file_byte_offset": 131072,
    "message_file_byte_total": -1,
    "message_file_id": "Os4wFar9tIT3B4iLcA/AsA8vPMU=",
    "message_max_buffer_size": 65536,
    "message_playback_id": "oVsbRzK3DZs4xZmuxiSyvw==",
    "message_position_ms": 1759,
    "message_target_buffer": 1048576,
    "message_total_prebuffer_ms": null,
    "message_track": "spotify:track:4m9NfjevXsDVaLtM1kj0Sx"
  },
  {
    "timestamp_utc": "2025-11-19T03:29:33.749Z",
    "context_application_version": "9.0.94.274",
    "context_conn_country": "AU",
    "context_device_manufacturer": "OPPO",
    "context_device_model": "CPH2625",
    "context_device_type": "mobile",
    "context_os_name": "android",
    "context_os_version": "15",
    "context_receiver_service_timestamp": 1763522986484,
    "context_time": 1763522973749,
    "message_audio_driver": "AndroidAudioDriver",
    "message_buffer_size": 0,
    "message_buffered_ms": 0,
    "message_driver_prebuffer_ms": null,
    "message_estimated_frame_loss": 0,
    "message_file_byte_offset": 819200,
    "message_file_byte_total": 2076272,
    "message_file_id": "dO1l/aajxelgQgVTmT20/dLp3Jg=",
    "message_max_buffer_size": 458752,
    "message_playback_id": "6MxN8w5wlhxmTgVmAcUDFg==",
    "message_position_ms": 74569,
    "message_target_buffer": 1048576,
    "message_total_prebuffer_ms": null,
    "message_track": "spotify:track:7yZD4AVfQtAZD4cG8eRnPk"
  }
]